{
    "pools": [
        {
            "name": "ancientbeasts:Witchcraft_3",
            "rolls": 1,
            "entries": [
                {
                    "type": "item",
                    "name": "ancientbeasts:water_rune",
                    "weight": 1
                }
            ]
        },
         {
                    "name": "ancientbeasts:Witchcraft_3",
                    "rolls": 1,
                    "entries": [

                        {
                            "type": "item",
                             "name": "ancientbeasts:hunters_eye",
                             "weight": 1
                        }
                    ]
         },
          {
                     "name": "ancientbeasts:Witchcraft_3",
                     "rolls": 1,
                     "entries": [

                         {
                              "type": "item",
                              "name": "ancientbeasts:tamers_charm",
                              "weight": 1
                         }
                     ]
         },
          {
                     "name": "ancientbeasts:Witchcraft_3",
                     "rolls": 1,
                     "entries": [

                         {
                             "type": "item",
                             "name": "ancientbeasts:protection_talisman",
                             "weight": 1
                         }
                     ]
          },
          {
                               "name": "ancientbeasts:Witchcraft_3",
                               "rolls": 1,
                               "entries": [

                                   {
                                       "type": "item",
                                       "name": "ancientbeasts:warriors_lock",
                                       "weight": 1
                                   }
                               ]
          },
      {
        "name": "ancientbeasts:Witchcraft_3",
        "rolls": 1,
        "entries": [

          {
            "type": "item",
            "name": "ancientbeasts:hungry_tooth",
            "weight": 1
          }
        ]
      }
    ]
}